shmedis/__init__.py
shmedis/core.py
shmedis/data_type.py
shmedis/index_hash_table.py
shmedis/lock.py
shmedis/skip_list.py
shmedis-0.3.8.dist-info/licenses/LICENSE-APACHE
shmedis-0.3.8.dist-info/METADATA
shmedis-0.3.8.dist-info/WHEEL
shmedis-0.3.8.dist-info/top_level.txt
shmedis-0.3.8.dist-info/RECORD
